tbcscrapper/__init__.py
tbcscrapper/__main__.py
tbcscrapper/bookscrapper.py
tbcscrapper/textbookcentreGUI.py
dentoscrapper-0.1.4.dist-info/LICENSE.txt
dentoscrapper-0.1.4.dist-info/METADATA
dentoscrapper-0.1.4.dist-info/WHEEL
dentoscrapper-0.1.4.dist-info/top_level.txt
dentoscrapper-0.1.4.dist-info/RECORD
