Metadata-Version: 2.1
Name: dentoscrapper
Version: 0.1.4
Summary: Useful tools for scrapping textbook centre images
Home-page: https://github.com/Denniskamau/TextbookcentreWebScrapper
Author: Dennis Kamau
Author-email: denniskamau3@gmail.com
License: MIT
Download-URL: https://pypi.org/project/dento-scrapper/
Keywords: WebSrapper,Data Mining,Textbook centre,Web scrapping
Platform: UNKNOWN
Requires-Dist: pysimplegui
Requires-Dist: beautifulsoup4
